Orange_Widget_Core-0.0.2.dist-info/DESCRIPTION.rst
Orange_Widget_Core-0.0.2.dist-info/METADATA
Orange_Widget_Core-0.0.2.dist-info/metadata.json
Orange_Widget_Core-0.0.2.dist-info/RECORD
Orange_Widget_Core-0.0.2.dist-info/top_level.txt
Orange_Widget_Core-0.0.2.dist-info/WHEEL
orangewidget/__init__.py
orangewidget/gui.py
orangewidget/settings.py
orangewidget/widget.py
orangewidget/canvas/__init__.py
orangewidget/canvas/config.py
orangewidget/canvas/discovery.py
orangewidget/canvas/workflow.py
orangewidget/icons/Dlg_arrow.png
orangewidget/icons/Dlg_clear.png
orangewidget/icons/Dlg_down3.png
orangewidget/icons/Dlg_enter.png
orangewidget/icons/Dlg_pan_hand.png
orangewidget/icons/Dlg_redo.png
orangewidget/icons/Dlg_send.png
orangewidget/icons/Dlg_sort.png
orangewidget/icons/Dlg_undo.png
orangewidget/icons/Dlg_up3.png
orangewidget/icons/Dlg_zoom.png
orangewidget/icons/Dlg_zoom_reset.png
orangewidget/icons/Dlg_zoom_selection.png
orangewidget/icons/downgreenarrow.png
orangewidget/icons/error.png
orangewidget/icons/information.png
orangewidget/icons/Unknown.png
orangewidget/icons/upgreenarrow.png
orangewidget/icons/warning.png
