Metadata-Version: 2.0
Name: Orange-Widget-Core
Version: 0.0.2
Summary: Core orange widget utilities
Home-page: http://orange.biolab.si/
Author: Bioinformatics Laboratory, FRI UL
Author-email: contact@orange.biolab.si
License: GPLv3
Platform: UNKNOWN
Requires-Dist: setuptools
Requires-Dist: orange-canvas-core (>=0.0.6,<0.1)
